<?xml version="1.0" encoding="UTF-8"?>
<CommandInterface xmlns="http://v8.1c.ru/8.3/xcf/extrnprops" xmlns:xr="http://v8.1c.ru/8.3/xcf/readable" xmlns:xs="http://www.w3.org/2001/XMLSchema" xmlns:xsi="http://www.w3.org/2001/XMLSchema-instance" version="2.20">
	<CommandsVisibility>
		<Command name="Document.Сделка.StandardCommand.OpenList">
			<Visibility>
				<xr:Common>true</xr:Common>
			</Visibility>
		</Command>
		<Command name="AccumulationRegister.ПозицииИнструментов.StandardCommand.OpenList">
			<Visibility>
				<xr:Common>true</xr:Common>
			</Visibility>
		</Command>
		<Command name="AccumulationRegister.ФинансовыеРезультатыПоСделкам.StandardCommand.OpenList">
			<Visibility>
				<xr:Common>true</xr:Common>
			</Visibility>
		</Command>
		<Command name="Document.Сделка.StandardCommand.Create">
			<Visibility>
				<xr:Common>true</xr:Common>
			</Visibility>
		</Command>
		<Command name="Catalog.Инструменты.StandardCommand.Create">
			<Visibility>
				<xr:Common>true</xr:Common>
			</Visibility>
		</Command>
		<Command name="Report.Обороты.StandardCommand.Open">
			<Visibility>
				<xr:Common>true</xr:Common>
			</Visibility>
		</Command>
		<Command name="Report.ПозицииНаДату.StandardCommand.Open">
			<Visibility>
				<xr:Common>true</xr:Common>
			</Visibility>
		</Command>
		<Command name="Report.Портфель.StandardCommand.Open">
			<Visibility>
				<xr:Common>true</xr:Common>
			</Visibility>
		</Command>
		<Command name="Report.РезультатыПродаж.StandardCommand.Open">
			<Visibility>
				<xr:Common>true</xr:Common>
			</Visibility>
		</Command>
		<Command name="Report.СводныйРеализованныйРезультат.StandardCommand.Open">
			<Visibility>
				<xr:Common>true</xr:Common>
			</Visibility>
		</Command>
		<Command name="Report.ЭффективностьСтратегий.StandardCommand.Open">
			<Visibility>
				<xr:Common>true</xr:Common>
			</Visibility>
		</Command>
	</CommandsVisibility>
	<CommandsPlacement>
		<Command name="Document.Сделка.StandardCommand.OpenList">
			<CommandGroup>NavigationPanelOrdinary</CommandGroup>
			<Placement>Manual</Placement>
		</Command>
		<Command name="AccumulationRegister.ПозицииИнструментов.StandardCommand.OpenList">
			<CommandGroup>NavigationPanelSeeAlso</CommandGroup>
			<Placement>Manual</Placement>
		</Command>
		<Command name="AccumulationRegister.ФинансовыеРезультатыПоСделкам.StandardCommand.OpenList">
			<CommandGroup>NavigationPanelSeeAlso</CommandGroup>
			<Placement>Manual</Placement>
		</Command>
		<Command name="Document.Сделка.StandardCommand.Create">
			<CommandGroup>ActionsPanelCreate</CommandGroup>
			<Placement>Manual</Placement>
		</Command>
		<Command name="Catalog.Инструменты.StandardCommand.Create">
			<CommandGroup>ActionsPanelCreate</CommandGroup>
			<Placement>Manual</Placement>
		</Command>
		<Command name="Report.Обороты.StandardCommand.Open">
			<CommandGroup>ActionsPanelReports</CommandGroup>
			<Placement>Manual</Placement>
		</Command>
		<Command name="Report.ПозицииНаДату.StandardCommand.Open">
			<CommandGroup>ActionsPanelReports</CommandGroup>
			<Placement>Manual</Placement>
		</Command>
		<Command name="Report.Портфель.StandardCommand.Open">
			<CommandGroup>ActionsPanelReports</CommandGroup>
			<Placement>Manual</Placement>
		</Command>
		<Command name="Report.РезультатыПродаж.StandardCommand.Open">
			<CommandGroup>ActionsPanelReports</CommandGroup>
			<Placement>Manual</Placement>
		</Command>
		<Command name="Report.СводныйРеализованныйРезультат.StandardCommand.Open">
			<CommandGroup>ActionsPanelReports</CommandGroup>
			<Placement>Manual</Placement>
		</Command>
		<Command name="Report.ЭффективностьСтратегий.StandardCommand.Open">
			<CommandGroup>ActionsPanelReports</CommandGroup>
			<Placement>Manual</Placement>
		</Command>
	</CommandsPlacement>
	<CommandsOrder>
		<Command name="Document.Сделка.StandardCommand.OpenList">
			<CommandGroup>NavigationPanelOrdinary</CommandGroup>
		</Command>
		<Command name="AccumulationRegister.ПозицииИнструментов.StandardCommand.OpenList">
			<CommandGroup>NavigationPanelSeeAlso</CommandGroup>
		</Command>
		<Command name="AccumulationRegister.ФинансовыеРезультатыПоСделкам.StandardCommand.OpenList">
			<CommandGroup>NavigationPanelSeeAlso</CommandGroup>
		</Command>
		<Command name="Document.Сделка.StandardCommand.Create">
			<CommandGroup>ActionsPanelCreate</CommandGroup>
		</Command>
		<Command name="Catalog.Инструменты.StandardCommand.Create">
			<CommandGroup>ActionsPanelCreate</CommandGroup>
		</Command>
	</CommandsOrder>
	<GroupsOrder>
		<Group>NavigationPanelOrdinary</Group>
		<Group>NavigationPanelSeeAlso</Group>
		<Group>ActionsPanelCreate</Group>
	</GroupsOrder>
</CommandInterface>